TeaRoute/__init__.py
TeaRoute/main.py
TeaRoute/router/__init__.py
TeaRoute/router/inner.py
TeaRoute/router/db/__init__.py
TeaRoute/router/manual/__init__.py
TeaRoute/router/manual/error.py
TeaRoute/router/manual/functions.py
TeaRoute/router/methods/__init__.py
TeaRoute/router/methods/chat.py
TeaRoute/router/methods/cos.py
TeaRoute/router/methods/embed.py
TeaRoute/router/methods/route.py
TeaRoute/router/methods/training.py
TeaRoute-0.0.9.dist-info/METADATA
TeaRoute-0.0.9.dist-info/WHEEL
TeaRoute-0.0.9.dist-info/top_level.txt
TeaRoute-0.0.9.dist-info/RECORD
